llama_index_alloydb_pg/__init__.py
llama_index_alloydb_pg/async_chat_store.py
llama_index_alloydb_pg/async_document_store.py
llama_index_alloydb_pg/async_index_store.py
llama_index_alloydb_pg/async_reader.py
llama_index_alloydb_pg/async_vector_store.py
llama_index_alloydb_pg/chat_store.py
llama_index_alloydb_pg/document_store.py
llama_index_alloydb_pg/engine.py
llama_index_alloydb_pg/index_store.py
llama_index_alloydb_pg/indexes.py
llama_index_alloydb_pg/py.typed
llama_index_alloydb_pg/reader.py
llama_index_alloydb_pg/vector_store.py
llama_index_alloydb_pg/version.py
llama_index_alloydb_pg-0.3.0.dist-info/licenses/LICENSE
llama_index_alloydb_pg-0.3.0.dist-info/METADATA
llama_index_alloydb_pg-0.3.0.dist-info/WHEEL
llama_index_alloydb_pg-0.3.0.dist-info/top_level.txt
llama_index_alloydb_pg-0.3.0.dist-info/RECORD
