Metadata-Version: 2.4
Name: llama-index-alloydb-pg
Version: 0.3.0
Summary: LlamaIndex integrations for Google Cloud AlloyDB for PostgreSQL
Author-email: Google LLC <googleapis-packages@google.com>
License:                                  Apache License
Project-URL: Homepage, https://github.com/googleapis/llama-index-alloydb-pg-python
Project-URL: Repository, https://github.com/googleapis/llama-index-alloydb-pg-python.git
Project-URL: Bug Tracker, https://github.com/googleapis/llama-index-alloydb-pg-python/issues
Project-URL: Changelog, https://github.com/googleapis/llama-index-alloydb-pg-python/blob/main/CHANGELOG.md
Classifier: Intended Audience :: Developers
Classifier: License :: OSI Approved :: Apache Software License
Classifier: Programming Language :: Python
Classifier: Programming Language :: Python :: 3
Classifier: Programming Language :: Python :: 3.10
Classifier: Programming Language :: Python :: 3.11
Classifier: Programming Language :: Python :: 3.12
Classifier: Programming Language :: Python :: 3.13
Requires-Python: >=3.10
License-File: LICENSE
Requires-Dist: google-cloud-alloydb-connector[asyncpg]<2.0.0,>=1.2.0
Requires-Dist: pgvector<1.0.0,>=0.2.5
Requires-Dist: SQLAlchemy[asyncio]<3.0.0,>=2.0.25
Requires-Dist: llama-index-core<1.0.0,>=0.12.0
Provides-Extra: test
Requires-Dist: black[jupyter]==25.12.0; extra == "test"
Requires-Dist: isort==7.0.0; extra == "test"
Requires-Dist: mypy==1.19.1; extra == "test"
Requires-Dist: pytest-asyncio==1.3.0; extra == "test"
Requires-Dist: pytest==9.0.2; extra == "test"
Requires-Dist: pytest-cov==7.0.0; extra == "test"
Requires-Dist: pytest-depends==1.0.1; extra == "test"
Dynamic: license-file
